{
  "markets": {
    "crypto": {
      "symbols": ["BTCUSD", "ETHUSD", "LTCUSD"],
      "timeframes": ["5m", "15m", "1h"]
    },
    "forex": {
      "symbols": ["EURUSD", "GBPUSD", "USDJPY"],
      "timeframes": ["5m", "15m", "1h"]
    },
    "equities": {
      "symbols": ["AAPL", "MSFT", "NVDA", "GOOGL", "AMZN", "TSLA"],
      "timeframes": ["5m", "15m", "1h"]
    },
    "indices": {
      "symbols": ["US500", "NAS100", "GER40", "UK100", "JPN225", "AUS200"],
      "timeframes": ["5m", "15m", "1h"]
    },
    "commodities": {
      "symbols": ["XAUUSD", "XAGUSD", "COPPER", "NATGAS"],
      "timeframes": ["5m", "15m", "1h"]
    }
  },
  "source": {
    "provider": "dukascopy-node",
    "format": "csv",
    "timezone": "UTC"
  },
  "ingestion": {
    "from": "2024-01-01",
    "to": "2024-12-31",
    "output_dir": "data/dukascopy",
    "timeout_seconds": 180
  }
}
